odoo/addons/website_geoengine_store_locator/README.rst
odoo/addons/website_geoengine_store_locator/__init__.py
odoo/addons/website_geoengine_store_locator/__manifest__.py
odoo/addons/website_geoengine_store_locator/i18n/it.po
odoo/addons/website_geoengine_store_locator/i18n/website_geoengine_store_locator.pot
odoo/addons/website_geoengine_store_locator/readme/CONFIGURE.rst
odoo/addons/website_geoengine_store_locator/readme/CONTRIBUTORS.rst
odoo/addons/website_geoengine_store_locator/readme/DESCRIPTION.rst
odoo/addons/website_geoengine_store_locator/readme/USAGE.rst
odoo/addons/website_geoengine_store_locator/static/styles.css
odoo/addons/website_geoengine_store_locator/static/description/icon.png
odoo/addons/website_geoengine_store_locator/static/description/index.html
odoo/addons/website_geoengine_store_locator/static/description/screencast.gif
odoo/addons/website_geoengine_store_locator/static/description/snippet.png
odoo/addons/website_geoengine_store_locator/static/description/snippet_configuration.png
odoo/addons/website_geoengine_store_locator/static/description/store_type.png
odoo/addons/website_geoengine_store_locator/static/lib/.gitignore
odoo/addons/website_geoengine_store_locator/static/lib/package.json
odoo/addons/website_geoengine_store_locator/static/lib/node_modules/jquery-flexdatalist/jquery.flexdatalist.css
odoo/addons/website_geoengine_store_locator/static/lib/node_modules/jquery-flexdatalist/jquery.flexdatalist.js
odoo/addons/website_geoengine_store_locator/static/lib/node_modules/ol/ol.css
odoo/addons/website_geoengine_store_locator/static/lib/node_modules/ol/dist/ol.js
odoo/addons/website_geoengine_store_locator/static/lib/node_modules/ol/dist/ol.js.map
odoo/addons/website_geoengine_store_locator/static/src/img/snippets_thumbs/s_openlayer_store_locator.png
odoo/addons/website_geoengine_store_locator/static/src/js/snippets/s_openlayer_store_locator/frontend.esm.js
odoo_addon_website_geoengine_store_locator-16.0.1.0.0.4.dist-info/METADATA
odoo_addon_website_geoengine_store_locator-16.0.1.0.0.4.dist-info/WHEEL
odoo_addon_website_geoengine_store_locator-16.0.1.0.0.4.dist-info/top_level.txt
odoo_addon_website_geoengine_store_locator-16.0.1.0.0.4.dist-info/RECORD
